data_toolkit-2.0.4.data/data/zshrc.txt
dt/__init__.py
dt/help.py
dt/main.py
dt/controllers/__init__.py
dt/controllers/base.py
dt/core/__init__.py
dt/core/data_diff.py
dt/core/exc.py
dt/core/version.py
dt/ext/__init__.py
dt/ext/asana.py
dt/ext/aws_ec2.py
dt/ext/aws_s3.py
dt/ext/aws_s3_list.py
dt/ext/aws_sg.py
dt/ext/codex.py
dt/ext/config.py
dt/ext/fake_data.py
dt/ext/faker.py
dt/ext/firelit.py
dt/ext/gcp.py
dt/ext/gdrive_dl.py
dt/ext/github.py
dt/ext/gkeep.py
dt/ext/hist.py
dt/ext/monitor.py
dt/ext/ms_outlook.py
dt/ext/notes.py
dt/ext/notions.py
dt/ext/openai_helper.py
dt/ext/python_exec.py
dt/ext/run.py
dt/ext/sftp_conf.py
dt/ext/ssh_params.py
dt/ext/sshconf.py
dt/ext/tracking.py
dt/ext/tree.py
dt/ext/youtube.py
dt/ext/zshrc.txt
dt/plugins/__init__.py
dt/plugins/viz_utils.py
dt/templates/__init__.py
dt/templates/command1.jinja2
dt/templates/sftp.json
data_toolkit-2.0.4.dist-info/LICENSE.md
data_toolkit-2.0.4.dist-info/METADATA
data_toolkit-2.0.4.dist-info/WHEEL
data_toolkit-2.0.4.dist-info/entry_points.txt
data_toolkit-2.0.4.dist-info/top_level.txt
data_toolkit-2.0.4.dist-info/RECORD
