Metadata-Version: 2.2
Name: data-toolkit
Version: 2.0.4
Summary: ML & data helper code!
Home-page: https://github.com/jakublangr/data-toolkit/
Author: Jakub Langr
Author-email: james.langr@gmail.com
License: (c) Jakub Langr
Requires-Python: >=3.6
License-File: LICENSE.md
Requires-Dist: cement>=3.0.8
Requires-Dist: jinja2
Requires-Dist: pyyaml
Requires-Dist: colorlog
Requires-Dist: sentry_sdk
Requires-Dist: gputil
Requires-Dist: streamlit
Requires-Dist: joblib
Requires-Dist: boto3
Requires-Dist: pandas
Requires-Dist: regex
Requires-Dist: pandas
Requires-Dist: boto3
Requires-Dist: pyyaml
Requires-Dist: colorlog
Requires-Dist: jinja2
Requires-Dist: humanize
Requires-Dist: PyGithub>=2.1.1
Requires-Dist: PyNaCl>=1.5.0
Requires-Dist: tabulate
Dynamic: author
Dynamic: author-email
Dynamic: description
Dynamic: description-content-type
Dynamic: home-page
Dynamic: license
Dynamic: requires-dist
Dynamic: requires-python
Dynamic: summary
